{"guide_browser.md":"6c5c1c7a","guide_canvas.md":"5c78920d","guide_cookie.md":"6ae4b494","guide_device.md":"d3b852cb","guide_editmd.md":"9a96cdfe","guide_event.md":"ded26d4d","guide_fn.md":"5f78c0cc","guide_media.md":"2da4622a","guide_number.md":"de296621","guide_plugins.md":"4ba6be6d","guide_polyfill.md":"5b47308c","guide_random.md":"b9df91ea","guide_regex.md":"55b4c033","guide_storage.md":"ad907be4","guide_string.md":"37fb7ee3","guide_time.md":"72df6e1a","guide_tools.md":"e3289f97","guide_url.md":"fceda58e","guide_index.md":"4343fbd9","guide_start.md":"8c64679d","index.md":"a3bad970"}
