{"guide_browser.md":"575216c3","guide_canvas.md":"5cb45efa","guide_cookie.md":"8c057c2d","guide_device.md":"528d56bd","guide_editmd.md":"2c158de8","guide_event.md":"579f8c3d","guide_fn.md":"c2e75067","guide_media.md":"33209179","guide_number.md":"44e9a582","guide_plugins.md":"1021e2ff","guide_polyfill.md":"485139a6","guide_random.md":"bb068f31","guide_regex.md":"bf7f42e3","guide_storage.md":"6980a4e3","guide_string.md":"fe432ece","guide_time.md":"ac767c5f","guide_tools.md":"44cd929f","guide_url.md":"12f49779","guide_index.md":"f8a2f374","guide_start.md":"b4f2a038","index.md":"82eae13f"}
